{"header": {"type": "esearch", "version": "0.3"}, "esearchresult": {"count": "174", "retmax": "10", "retstart": "0", "querykey": "1", "webenv": "NCID_1_154811012_130.14.18.34_9001_1535811103_1769414542_0MetA0_S_MegaStore", "idlist": ["30170239", "30168362", "30166777", "30160601", "30160377", "30160372", "30159149", "30158820", "30158816", "30153984"], "translationset": [{"from": "Emotional", "to": "\"emotions\"[MeSH Terms] OR \"emotions\"[All Fields] OR \"emotional\"[All Fields]"}], "translationstack": [{"term": "\"emotions\"[MeSH Terms]", "field": "MeSH Terms", "count": "216500", "explode": "Y"}, {"term": "\"emotions\"[All Fields]", "field": "All Fields", "count": "74424", "explode": "N"}, "OR", {"term": "\"emotional\"[All Fields]", "field": "All Fields", "count": "133705", "explode": "N"}, "OR", "GROUP", {"term": "distress[All Fields]", "field": "All Fields", "count": "114114", "explode": "N"}, "AND", "GROUP", {"term": "2018/07/03[EDAT]", "field": "EDAT", "count": "0", "explode": "N"}, {"term": "2018/09/01[EDAT]", "field": "EDAT", "count": "0", "explode": "N"}, "RANGE", "AND"], "querytranslation": "((\"emotions\"[MeSH Terms] OR \"emotions\"[All Fields] OR \"emotional\"[All Fields]) AND distress[All Fields]) AND 2018/07/03[EDAT] : 2018/09/01[EDAT]"}}