{"header": {"type": "esearch", "version": "0.3"}, "esearchresult": {"count": "93", "retmax": "10", "retstart": "0", "querykey": "1", "webenv": "NCID_1_24117703_130.14.18.125_9001_1535986637_500397870_0MetA0_S_MegaStore", "idlist": ["30169554", "30169422", "30168855", "30166973", "30161182", "30158242", "30156115", "30155840", "30154243", "30154101"], "translationset": [{"from": "activity", "to": "\"motor activity\"[MeSH Terms] OR (\"motor\"[All Fields] AND \"activity\"[All Fields]) OR \"motor activity\"[All Fields] OR \"activity\"[All Fields]"}, {"from": "calcium channel", "to": "\"calcium channels\"[MeSH Terms] OR (\"calcium\"[All Fields] AND \"channels\"[All Fields]) OR \"calcium channels\"[All Fields] OR (\"calcium\"[All Fields] AND \"channel\"[All Fields]) OR \"calcium channel\"[All Fields]"}], "translationstack": [{"term": "\"calcium channels\"[MeSH Terms]", "field": "MeSH Terms", "count": "40332", "explode": "Y"}, {"term": "\"calcium\"[All Fields]", "field": "All Fields", "count": "565059", "explode": "N"}, {"term": "\"channels\"[All Fields]", "field": "All Fields", "count": "228198", "explode": "N"}, "AND", "GROUP", "OR", {"term": "\"calcium channels\"[All Fields]", "field": "All Fields", "count": "39739", "explode": "N"}, "OR", {"term": "\"calcium\"[All Fields]", "field": "All Fields", "count": "565059", "explode": "N"}, {"term": "\"channel\"[All Fields]", "field": "All Fields", "count": "248309", "explode": "N"}, "AND", "GROUP", "OR", {"term": "\"calcium channel\"[All Fields]", "field": "All Fields", "count": "54154", "explode": "N"}, "OR", "GROUP", {"term": "\"motor activity\"[MeSH Terms]", "field": "MeSH Terms", "count": "260002", "explode": "Y"}, {"term": "\"motor\"[All Fields]", "field": "All Fields", "count": "399548", "explode": "N"}, {"term": "\"activity\"[All Fields]", "field": "All Fields", "count": "2580018", "explode": "N"}, "AND", "GROUP", "OR", {"term": "\"motor activity\"[All Fields]", "field": "All Fields", "count": "101499", "explode": "N"}, "OR", {"term": "\"activity\"[All Fields]", "field": "All Fields", "count": "2580018", "explode": "N"}, "OR", "GROUP", "AND", "GROUP", {"term": "2018/07/05[EDAT]", "field": "EDAT", "count": "0", "explode": "N"}, {"term": "2018/09/03[EDAT]", "field": "EDAT", "count": "0", "explode": "N"}, "RANGE", "AND"], "querytranslation": "((\"calcium channels\"[MeSH Terms] OR (\"calcium\"[All Fields] AND \"channels\"[All Fields]) OR \"calcium channels\"[All Fields] OR (\"calcium\"[All Fields] AND \"channel\"[All Fields]) OR \"calcium channel\"[All Fields]) AND (\"motor activity\"[MeSH Terms] OR (\"motor\"[All Fields] AND \"activity\"[All Fields]) OR \"motor activity\"[All Fields] OR \"activity\"[All Fields])) AND 2018/07/05[EDAT] : 2018/09/03[EDAT]"}}